traffic_light/__init__.py
traffic_light/__main__.py
traffic_light/core.py
traffic_light/error.py
cleware_traffic_light-1.0.8.dist-info/LICENSE
cleware_traffic_light-1.0.8.dist-info/METADATA
cleware_traffic_light-1.0.8.dist-info/WHEEL
cleware_traffic_light-1.0.8.dist-info/entry_points.txt
cleware_traffic_light-1.0.8.dist-info/top_level.txt
cleware_traffic_light-1.0.8.dist-info/RECORD
