Metadata-Version: 2.1
Name: cleware-traffic-light
Version: 1.0.8
Summary: Python3 modul and cli tool to controll the Cleware traffic light
Home-page: https://github.com/joshrost/cleware-traffic-light
Author: Josh Rost
Author-email: joshua.s.rost@gmail.com
License: UNKNOWN
Platform: UNKNOWN
Requires-Dist: pyusb
